[{"name":"Oliver ","team":"Bayern Munich","age":"45","num":"(1)","lastname":"Kahn "},{"name":"Jens ","team":"Borussia Dortmund","age":"14","num":"(12)","lastname":"Lehmann "},{"name":"Hans-Jörg ","team":"Bayer Leverkusen","age":"2","num":"(23)","lastname":"Butt "},{"name":"Thomas ","team":"Bayern Munich","age":"34","num":" (2)","lastname":"Linke "},{"name":"Marko ","team":"Hertha BSC","age":"27","num":" (3)","lastname":"Rehmer "},{"name":"Frank ","team":"Werder Bremen","age":"11","num":" (4)","lastname":"Baumann "},{"name":"Christian ","team":"Tottenham Hotspur","age":"66","num":" (6)","lastname":"Ziege "},{"name":"Sebastian ","team":"Borussia Dortmund","age":"8","num":"(15)","lastname":"Kehl "},{"name":"Christoph ","team":"Borussia Dortmund","age":"6","num":"(21)","lastname":"Metzelder "},{"name":"Carsten ","team":"Bayer Leverkusen","age":"25","num":" (5)","lastname":"Ramelow "},{"name":"Dietmar ","team":"Liverpool","age":"40","num":" (8)","lastname":"Hamann "},{"name":"Lars ","team":"Borussia Dortmund","age":"16","num":"(10)","lastname":"Ricken "},{"name":"Michael ","team":"Bayer Leverkusen","age":"22","num":"(13)","lastname":"Ballack "},{"name":"Jens ","team":"Bayern Munich","age":"33","num":"(16)","lastname":"Jeremies "},{"name":"Marco ","team":"Werder Bremen","age":"34","num":"(17)","lastname":"Bode "},{"name":"Jörg ","team":"Schalke 04","age":"6","num":"(18)","lastname":"Böhme "},{"name":"Bernd ","team":"Bayer Leverkusen","age":"9","num":"(19)","lastname":"Schneider "},{"name":"Torsten ","team":"Werder Bremen","age":"8","num":"(22)","lastname":"Frings "},{"name":"Oliver ","team":"Bayer Leverkusen","age":"30","num":" (7)","lastname":"Neuville "},{"name":"Carsten ","team":"Bayern Munich","age":"26","num":" (9)","lastname":"Jancker "},{"name":"Miroslav ","team":"1. FC Kaiserslautern","age":"12","num":"(11)","lastname":"Klose "},{"name":"Gerald ","team":"Schalke 04","age":"11","num":"(14)","lastname":"Asamoah "},{"name":"Oliver ","team":"AS Monaco","age":"65","num":"(20)","lastname":"Bierhoff "}]